spotifind/__init__.py
spotifind/spotifind.py
spotifind-0.0.6.dist-info/LICENSE
spotifind-0.0.6.dist-info/METADATA
spotifind-0.0.6.dist-info/WHEEL
spotifind-0.0.6.dist-info/entry_points.txt
spotifind-0.0.6.dist-info/top_level.txt
spotifind-0.0.6.dist-info/RECORD
