Metadata-Version: 2.1
Name: spotifind
Version: 0.0.6
Summary: Spotify and Tunefind Bridge Simple CLI
Home-page: https://github.com/samapriya/spotifind
Author: Samapriya Roy
Author-email: samapriya.roy@gmail.com
License: Apache 2.0
Platform: UNKNOWN
Classifier: Development Status :: 3 - Alpha
Classifier: Intended Audience :: Developers
Classifier: Intended Audience :: Science/Research
Classifier: Natural Language :: English
Classifier: License :: OSI Approved :: Apache Software License
Classifier: Programming Language :: Python :: 3
Classifier: Programming Language :: Python :: 3.6
Classifier: Programming Language :: Python :: 3.7
Classifier: Programming Language :: Python :: 3.8
Classifier: Operating System :: OS Independent
Requires-Python: >=3.2
Requires-Dist: requests (>=2.21.1)
Requires-Dist: logzero (>=1.5.0)
Requires-Dist: beautifulsoup4 (>=4.8.2)
Requires-Dist: rapidfuzz (>=1.5.0)
